odoo/addons/hr_expense_journal/README.rst
odoo/addons/hr_expense_journal/__init__.py
odoo/addons/hr_expense_journal/__manifest__.py
odoo/addons/hr_expense_journal/i18n/hr_expense_journal.pot
odoo/addons/hr_expense_journal/i18n/it.po
odoo/addons/hr_expense_journal/models/__init__.py
odoo/addons/hr_expense_journal/models/account_payment_method_line.py
odoo/addons/hr_expense_journal/models/hr_expense.py
odoo/addons/hr_expense_journal/readme/CONTRIBUTORS.md
odoo/addons/hr_expense_journal/readme/DESCRIPTION.md
odoo/addons/hr_expense_journal/readme/USAGE.md
odoo/addons/hr_expense_journal/static/description/icon.png
odoo/addons/hr_expense_journal/static/description/index.html
odoo/addons/hr_expense_journal/tests/__init__.py
odoo/addons/hr_expense_journal/tests/test_hr_expense_journal.py
odoo/addons/hr_expense_journal/views/hr_expense_views.xml
odoo_addon_hr_expense_journal-17.0.1.0.0.2.dist-info/METADATA
odoo_addon_hr_expense_journal-17.0.1.0.0.2.dist-info/WHEEL
odoo_addon_hr_expense_journal-17.0.1.0.0.2.dist-info/top_level.txt
odoo_addon_hr_expense_journal-17.0.1.0.0.2.dist-info/RECORD
